{
    "source": {
        "content": "【#社会志异#两男子约女网友见面被误解偷小孩遭村民围殴！】3日网传河北蠡县两疑似偷小”男子，被千人殴打，车被掀翻。4日蠡县宣传部通报：张某、王某来见女网友李某。李某儿子独自在家，张某带其上车找李某，被村民误解为偷孩子。【评】小编觉得这种误解是完全可以理解的！ 网页链接 ",
        "time": "16-12-4 17:56",
        "user id": "5133081104",
        "tweet id": "EkzgC5GOV",
        "label": 0,
        "theme": "社会生活"
    },
    "comment": [
        {
            "comment id": 0,
            "parent": -1,
            "children": [
                1
            ],
            "user id": "2901684451",
            "user name": "米仙君",
            "content": "我就想最后这该怎么判，所有损失有谁负责。",
            "time": "16-12-4 20:25",
            "stance_label": 1,
            "state": 1,
            "hop": 1
        },
        {
            "comment id": 1,
            "parent": 0,
            "children": [],
            "user id": "2590112321",
            "user name": "旁观者经过",
            "content": "@旁观者经过: 乡政府能赔点钱估计就是奇迹，村民个人不太可能赔钱，这男的到熟人社会的农村约人，也是找死，估计村民也可能明白这男的是来约泡的，但是为了顾及这女的丈夫脸面，不这样说而已。这男会成冤大头，砸了车没出人命就是菩萨保佑了",
            "time": "16-12-5 09:08",
            "stance_label": 1,
            "state": 0,
            "hop": 2
        },
        {
            "comment id": 2,
            "parent": -1,
            "children": [
                3
            ],
            "user id": "5039384743",
            "user name": "靠自己当女王w",
            "content": "大家别误会，我只是来约孩子他妈的",
            "time": "16-12-4 18:49",
            "stance_label": 1,
            "state": 1,
            "hop": 1
        },
        {
            "comment id": 3,
            "parent": 2,
            "children": [],
            "user id": "3841793492",
            "user name": "时缘V",
            "content": "我们这抓住了也会这样打",
            "time": "16-12-4 19:07",
            "stance_label": 0,
            "state": 1,
            "hop": 2
        },
        {
            "comment id": 4,
            "parent": -1,
            "children": [
                5
            ],
            "user id": "3033626947",
            "user name": "加贝哥",
            "content": "法治呢？",
            "time": "16-12-4 19:02",
            "stance_label": 1,
            "state": 1,
            "hop": 1
        },
        {
            "comment id": 5,
            "parent": 4,
            "children": [],
            "user id": "3841793492",
            "user name": "时缘V",
            "content": "这种就该打   搞别人老婆被抓",
            "time": "16-12-4 19:06",
            "stance_label": 0,
            "state": 1,
            "hop": 2
        },
        {
            "comment id": 6,
            "parent": -1,
            "children": [],
            "user id": "5104321234",
            "user name": "芊0000",
            "content": "我们这边的，不知说什么好！",
            "time": "16-12-5 11:20",
            "stance_label": 1,
            "state": 1,
            "hop": 1
        },
        {
            "comment id": 7,
            "parent": -1,
            "children": [],
            "user id": "2590112321",
            "user name": "旁观者经过",
            "content": "这事又解释不清，说约你们村某某女照样遭暴打",
            "time": "16-12-5 09:04",
            "stance_label": 1,
            "state": 1,
            "hop": 1
        },
        {
            "comment id": 8,
            "parent": -1,
            "children": [],
            "user id": "5091227227",
            "user name": "战神金鹰",
            "content": "厉害了",
            "time": "16-12-4 23:15",
            "stance_label": 0,
            "state": 0,
            "hop": 1
        },
        {
            "comment id": 9,
            "parent": -1,
            "children": [],
            "user id": "6059339927",
            "user name": "萌萌Cat猫",
            "content": "村民也没错，谁会想到约炮还带儿子的，要是这情况不管不顾要是真是偷小孩子的怎么办",
            "time": "16-12-12 10:00",
            "stance_label": 1,
            "state": 1,
            "hop": 1
        },
        {
            "comment id": 10,
            "parent": -1,
            "children": [],
            "user id": "6059339927",
            "user name": "萌萌Cat猫",
            "content": "约炮还带上儿子我也是醉了",
            "time": "16-12-12 09:58",
            "stance_label": 1,
            "state": 1,
            "hop": 1
        },
        {
            "comment id": 11,
            "parent": -1,
            "children": [],
            "user id": "6059339927",
            "user name": "萌萌Cat猫",
            "content": "贱人痒了，以后那家人没法抬头见人了",
            "time": "16-12-12 09:58",
            "stance_label": 1,
            "state": 1,
            "hop": 1
        },
        {
            "comment id": 12,
            "parent": -1,
            "children": [
                13
            ],
            "user id": "5284223196",
            "user name": "守护HRYY",
            "content": "看来热心的村民很多 但还是要搞清楚原因哦 不要误会就好",
            "time": "16-12-11 21:12",
            "stance_label": 0,
            "state": 0,
            "hop": 1
        },
        {
            "comment id": 13,
            "parent": 12,
            "children": [],
            "user id": "6059339927",
            "user name": "萌萌Cat猫",
            "content": "原因就是约炮还带小的",
            "time": "16-12-12 10:02",
            "stance_label": 1,
            "state": 1,
            "hop": 2
        },
        {
            "comment id": 14,
            "parent": -1,
            "children": [],
            "user id": "5264012521",
            "user name": "爱吃芒果的Crys",
            "content": "这种误解可以理解，无法接受和原谅。不然要法制干嘛呢？既然人人都可以实施私刑，那看谁不顺眼就可以找个理由把自己放在道德制高点然后直接打一顿咯？那么多人，堵住等警方来处理不就好了。聂树斌案的时候一个比一个骂的凶，这时候倒反过来支持村民打人掀车了？宁错杀一千不放过一个？脑子是个好东西。",
            "time": "16-12-5 10:36",
            "stance_label": 1,
            "state": 1,
            "hop": 1
        }
    ],
    "state": {
        "1-hop": {
            "state_0": 2,
            "state_1": 9
        },
        "2-hop": {
            "state_0": 1,
            "state_1": 3
        }
    }
}