{
    "source": {
        "content": "【中国双休日的来历】 1994年前后，中美入世谈判最艰难的时刻，美方突然向中方提出：在全世界都实行双休日的今天，中国必须尊重**，也给中国人双休日，并把这一项作为入世条件之一。1995年5月1日后起我国开始实行双休日工作制。❤喜欢请关注@神秘野史   ",
        "time": "12-10-21 21:12",
        "user id": "2133041565",
        "tweet id": "z1xEr80hL",
        "label": 1,
        "theme": null
    },
    "comment": [
        {
            "comment id": 0,
            "parent": -1,
            "children": [],
            "user id": "1141032227",
            "user name": "为宇筹眸",
            "content": "不可能，95年我已经五年级了，双休日是三年级开始的，也就是93年至94年间",
            "time": "12-11-3 01:41",
            "stance_label": 1,
            "state": 1,
            "hop": 1
        },
        {
            "comment id": 1,
            "parent": -1,
            "children": [],
            "user id": "1424332505",
            "user name": "兽性和人性",
            "content": "道个歉，我拆你的台了。@神秘野史",
            "time": "12-10-22 19:08",
            "stance_label": 0,
            "state": 0,
            "hop": 1
        },
        {
            "comment id": 2,
            "parent": -1,
            "children": [],
            "user id": "1227039891",
            "user name": "稻之道非常稻",
            "content": " @roxiess 感谢老美吧，不过目前这待遇不适用于我们！",
            "time": "12-10-22 00:25",
            "stance_label": 0,
            "state": 0,
            "hop": 1
        },
        {
            "comment id": 3,
            "parent": -1,
            "children": [],
            "user id": "2740012651",
            "user name": "风清-白兰2013",
            "content": "可怜啊…至今红星美凯龙深圳店很多都是一周休四天，还有直落的，投诉无门…怕丟工作一个个",
            "time": "12-10-21 23:43",
            "stance_label": 0,
            "state": 0,
            "hop": 1
        },
        {
            "comment id": 4,
            "parent": -1,
            "children": [],
            "user id": "1667817732",
            "user name": "苍穹下的小小鸟",
            "content": "【中国双休日的来历】 1994年前后，中美入世谈判最艰难的时刻，美方突然向中方提出：在全世界都实行双休日的今天，中国必须尊重**，也给中国人双休日，并把这一项作为入世条件之一。1995年5月1日后起我国开始实行双休日工作制。",
            "time": "12-10-21 23:40",
            "stance_label": 0,
            "state": 0,
            "hop": 1
        },
        {
            "comment id": 5,
            "parent": -1,
            "children": [],
            "user id": "1692237660",
            "user name": "耳立左",
            "content": "原来要感谢老美啊",
            "time": "12-10-21 23:19",
            "stance_label": 0,
            "state": 0,
            "hop": 1
        },
        {
            "comment id": 6,
            "parent": -1,
            "children": [],
            "user id": "1424332505",
            "user name": "兽性和人性",
            "content": "1995年申请加入世贸组织，2001年加入。怎么可能1994年是谈判的最关键时间？",
            "time": "12-10-21 23:04",
            "stance_label": 1,
            "state": 1,
            "hop": 1
        },
        {
            "comment id": 7,
            "parent": -1,
            "children": [],
            "user id": "1424332505",
            "user name": "兽性和人性",
            "content": "1995.7.11，中国正式提出加入世贸组织申请，2001年加入WTO。之前也在谈，但叫恢复关贸总协定缔约国地位。因此“入世”谈判从1995年开始的，1994还没有申请。实际上中国早就开始酝酿双休日了。详情: 网页链接。再说,并非全世界都实行双休日，比如香港就不是，香港星期六还要上班半天的。",
            "time": "12-10-21 23:03",
            "stance_label": 1,
            "state": 1,
            "hop": 1
        },
        {
            "comment id": 8,
            "parent": -1,
            "children": [],
            "user id": "2463457602",
            "user name": "昵称RW",
            "content": "真的吗?那岂不是全中国劳动人民要感谢老美!",
            "time": "12-10-21 23:00",
            "stance_label": 0,
            "state": 0,
            "hop": 1
        },
        {
            "comment id": 9,
            "parent": -1,
            "children": [],
            "user id": "2150168055",
            "user name": "两个XX的故事",
            "content": "啊",
            "time": "12-10-21 22:16",
            "stance_label": 0,
            "state": 0,
            "hop": 1
        },
        {
            "comment id": 10,
            "parent": -1,
            "children": [],
            "user id": "2440658861",
            "user name": "麥尒Maraba",
            "content": "转发微博",
            "time": "12-10-21 22:07",
            "stance_label": 0,
            "state": 0,
            "hop": 1
        },
        {
            "comment id": 11,
            "parent": -1,
            "children": [],
            "user id": "1233503854",
            "user name": "展翅深空",
            "content": "太经典了……借此想说美国人是好东西的人，不太像是好东西，",
            "time": "12-10-21 21:59",
            "stance_label": 0,
            "state": 0,
            "hop": 1
        },
        {
            "comment id": 12,
            "parent": -1,
            "children": [],
            "user id": "1771893157",
            "user name": "猫太狼的大灰灰",
            "content": "感谢美帝国主义！",
            "time": "12-10-21 21:47",
            "stance_label": 0,
            "state": 0,
            "hop": 1
        },
        {
            "comment id": 13,
            "parent": -1,
            "children": [],
            "user id": "2094794633",
            "user name": "血肉模糊的信仰",
            "content": "都21世纪了，我的双休呢？",
            "time": "12-10-21 21:41",
            "stance_label": 0,
            "state": 0,
            "hop": 1
        },
        {
            "comment id": 14,
            "parent": -1,
            "children": [],
            "user id": "1434961770",
            "user name": "墨香舫",
            "content": "说好的双休日呢? 艾特 勤劳的朋友们",
            "time": "12-10-21 21:41",
            "stance_label": 0,
            "state": 0,
            "hop": 1
        },
        {
            "comment id": 15,
            "parent": -1,
            "children": [],
            "user id": "1657670047",
            "user name": "孙伯然",
            "content": "中学生现在都缩水成半休了。。。看来我中国现在真是能顶半边“天”了呀",
            "time": "12-10-21 21:40",
            "stance_label": 0,
            "state": 0,
            "hop": 1
        },
        {
            "comment id": 16,
            "parent": -1,
            "children": [],
            "user id": "1446035241",
            "user name": "暖暖的西瓜地",
            "content": "是这么回事啊感谢美帝国主义",
            "time": "12-10-21 21:39",
            "stance_label": 0,
            "state": 0,
            "hop": 1
        },
        {
            "comment id": 17,
            "parent": -1,
            "children": [],
            "user id": "1887684700",
            "user name": "Zero-乔",
            "content": "不是吧？这点权利还是靠帝国主义争取的，我党。。。",
            "time": "12-10-21 21:37",
            "stance_label": 1,
            "state": 1,
            "hop": 1
        },
        {
            "comment id": 18,
            "parent": -1,
            "children": [],
            "user id": "1052318252",
            "user name": "小鱼689",
            "content": "我还没有享受过",
            "time": "12-10-21 21:37",
            "stance_label": 0,
            "state": 0,
            "hop": 1
        },
        {
            "comment id": 19,
            "parent": -1,
            "children": [],
            "user id": "2035981113",
            "user name": "看了再看再看",
            "content": "想到一起去了握个手",
            "time": "12-10-21 21:35",
            "stance_label": 0,
            "state": 0,
            "hop": 1
        },
        {
            "comment id": 20,
            "parent": -1,
            "children": [],
            "user id": "2035981113",
            "user name": "看了再看再看",
            "content": "万恶的帝国主义",
            "time": "12-10-21 21:34",
            "stance_label": 0,
            "state": 0,
            "hop": 1
        },
        {
            "comment id": 21,
            "parent": -1,
            "children": [],
            "user id": "1974892467",
            "user name": "yanyanmaya",
            "content": "万恶的美帝国主义",
            "time": "12-10-21 21:34",
            "stance_label": 0,
            "state": 0,
            "hop": 1
        },
        {
            "comment id": 22,
            "parent": -1,
            "children": [],
            "user id": "2012001314",
            "user name": "西門小貝_絕版少爺為食猫",
            "content": "感谢美帝普世价值，恩泽国民，果断转了@流艳飞鱼 @salvador2010 @囡囡困小猫 @洋娃娃和粒粒跳舞 @妍妍妍妍妍要做个快乐的小二货 @汆汤鱼NJ",
            "time": "12-10-21 21:34",
            "stance_label": 0,
            "state": 0,
            "hop": 1
        },
        {
            "comment id": 23,
            "parent": -1,
            "children": [],
            "user id": "1794202477",
            "user name": "一块云糕",
            "content": "",
            "time": "12-10-21 21:33",
            "stance_label": 0,
            "state": 0,
            "hop": 1
        },
        {
            "comment id": 24,
            "parent": -1,
            "children": [],
            "user id": "1412425440",
            "user name": "玛丝客",
            "content": "什么时候实行双工作日啊！？",
            "time": "12-10-21 21:33",
            "stance_label": 0,
            "state": 0,
            "hop": 1
        },
        {
            "comment id": 25,
            "parent": -1,
            "children": [],
            "user id": "1851534232",
            "user name": "月亮湾宝贝",
            "content": "是这样吗",
            "time": "12-10-21 21:27",
            "stance_label": 0,
            "state": 0,
            "hop": 1
        },
        {
            "comment id": 26,
            "parent": -1,
            "children": [],
            "user id": "2291481300",
            "user name": "棒子粥走江湖",
            "content": "原来如此",
            "time": "12-10-21 21:27",
            "stance_label": 0,
            "state": 0,
            "hop": 1
        },
        {
            "comment id": 27,
            "parent": -1,
            "children": [],
            "user id": "1742046090",
            "user name": "橱柜网事孟庆栋",
            "content": "这是真的",
            "time": "12-10-21 21:22",
            "stance_label": 0,
            "state": 0,
            "hop": 1
        },
        {
            "comment id": 28,
            "parent": -1,
            "children": [],
            "user id": "1801549785",
            "user name": "泡沫之夏2293",
            "content": "老板你看看。",
            "time": "12-10-21 21:21",
            "stance_label": 0,
            "state": 0,
            "hop": 1
        },
        {
            "comment id": 29,
            "parent": -1,
            "children": [],
            "user id": "2248398031",
            "user name": "UncleT0M",
            "content": "连这也与米帝有关？太TM颠覆了。",
            "time": "12-10-21 21:19",
            "stance_label": 1,
            "state": 1,
            "hop": 1
        },
        {
            "comment id": 30,
            "parent": -1,
            "children": [],
            "user id": "1268159280",
            "user name": "Danny0571",
            "content": "感谢，咱还有什么类似组织需要加入的吗？[挖鼻屎]",
            "time": "12-10-21 21:18",
            "stance_label": 0,
            "state": 0,
            "hop": 1
        },
        {
            "comment id": 31,
            "parent": -1,
            "children": [],
            "user id": "1768082544",
            "user name": "Evan刘星",
            "content": "感谢美帝",
            "time": "12-10-21 21:16",
            "stance_label": 0,
            "state": 0,
            "hop": 1
        },
        {
            "comment id": 32,
            "parent": -1,
            "children": [],
            "user id": "2085443773",
            "user name": "里口山的山",
            "content": "转发微博",
            "time": "12-10-21 21:16",
            "stance_label": 0,
            "state": 0,
            "hop": 1
        },
        {
            "comment id": 33,
            "parent": -1,
            "children": [],
            "user id": "1752906610",
            "user name": "西安魑魅魍魉",
            "content": "转发微博",
            "time": "12-10-21 21:15",
            "stance_label": 0,
            "state": 0,
            "hop": 1
        },
        {
            "comment id": 34,
            "parent": -1,
            "children": [],
            "user id": "2612123730",
            "user name": "飞导小李",
            "content": "真假的？我们的假日是美帝给的",
            "time": "12-10-21 21:13",
            "stance_label": 1,
            "state": 1,
            "hop": 1
        }
    ],
    "state": {
        "1-hop": {
            "state_0": 29,
            "state_1": 6
        }
    }
}