{
    "source": {
        "content": "Ferguson police chief speaks with protesters early Friday am. #ferguson http://t.co/uFHeK4MyxT",
        "user id": 2680112214,
        "tweet id": "500246996163129344",
        "label": 0
    },
    "comment": [
        {
            "comment id": 0,
            "parent": -1,
            "children": [
                1,
                2,
                3,
                4
            ],
            "content": "@CNNKatelyn I'm pretty much sure the police are the law....placard fail",
            "user id": 262094773,
            "user name": "",
            "stance_label": 1,
            "state": 1,
            "hop": 1
        },
        {
            "comment id": 1,
            "parent": 0,
            "children": [
                23
            ],
            "content": "@data1984 @cnnkatelyn Police are NOT the law. Just people put in place to uphold the law. Big difference.",
            "user id": 18274760,
            "user name": "",
            "stance_label": 1,
            "state": 0,
            "hop": 2
        },
        {
            "comment id": 2,
            "parent": 0,
            "children": [],
            "content": "@DATA1984 @CNNKatelyn Police are not the law. They just enforce the law. They do not decide what's legal though. Courts do that.",
            "user id": 2731516352,
            "user name": "",
            "stance_label": 1,
            "state": 0,
            "hop": 2
        },
        {
            "comment id": 3,
            "parent": 0,
            "children": [],
            "content": "@DATA1984  Upholding and enforcing the law does not make you the law. That's a dangerous precedent and gives police too much power.",
            "user id": 330964245,
            "user name": "",
            "stance_label": 1,
            "state": 0,
            "hop": 2
        },
        {
            "comment id": 4,
            "parent": 0,
            "children": [],
            "content": "@DATA1984 @CNNKatelyn They are not the law. They are responsible for enforcement of the law which they are bound to as well.",
            "user id": 2163599544,
            "user name": "",
            "stance_label": 1,
            "state": 0,
            "hop": 2
        },
        {
            "comment id": 5,
            "parent": -1,
            "children": [],
            "content": "@CNNKatelyn his fat ass should be talking to the people begging for his job",
            "user id": 2306547892,
            "user name": "",
            "stance_label": 0,
            "state": 0,
            "hop": 1
        },
        {
            "comment id": 6,
            "parent": -1,
            "children": [],
            "content": "@CNNKatelyn @CNN all people must thank this",
            "user id": 2703242611,
            "user name": "",
            "stance_label": 0,
            "state": 0,
            "hop": 1
        },
        {
            "comment id": 7,
            "parent": -1,
            "children": [],
            "content": "@CNNKatelyn @CNN lol not the law? What?",
            "user id": 2720798625,
            "user name": "",
            "stance_label": 1,
            "state": 1,
            "hop": 1
        },
        {
            "comment id": 8,
            "parent": -1,
            "children": [
                9
            ],
            "content": "@CNNKatelyn @CNN Cant call it a \"peaceful protest\" when protesters are holding signs saying there will be no peace unless they get \"justice\"",
            "user id": 2376893806,
            "user name": "",
            "stance_label": 1,
            "state": 1,
            "hop": 1
        },
        {
            "comment id": 9,
            "parent": 8,
            "children": [],
            "content": "@MericaMcFreedom @CNNKatelyn @CNN its called protest dummy.",
            "user id": 2231390008,
            "user name": "",
            "stance_label": 1,
            "state": 0,
            "hop": 2
        },
        {
            "comment id": 10,
            "parent": -1,
            "children": [],
            "content": "@CNNKatelyn Police don't make laws politicians make laws Police only interpret them, obviously they chose a bad interpretation this time",
            "user id": 138308568,
            "user name": "",
            "stance_label": 0,
            "state": 0,
            "hop": 1
        },
        {
            "comment id": 11,
            "parent": -1,
            "children": [],
            "content": "@CNNKatelyn @CNN does her sign say 'police are not the law?' What an idiot",
            "user id": 279610537,
            "user name": "",
            "stance_label": 0,
            "state": 0,
            "hop": 1
        },
        {
            "comment id": 12,
            "parent": -1,
            "children": [],
            "content": "@CNNKatelyn @CNN This Is Very Sad",
            "user id": 2610607914,
            "user name": "",
            "stance_label": 0,
            "state": 0,
            "hop": 1
        },
        {
            "comment id": 13,
            "parent": -1,
            "children": [],
            "content": "@CNNKatelyn @CNN how does one know what stories are media driven?  Watch cnn. Find that plane yet?",
            "user id": 408150347,
            "user name": "",
            "stance_label": 1,
            "state": 1,
            "hop": 1
        },
        {
            "comment id": 14,
            "parent": -1,
            "children": [],
            "content": "@CNNKatelyn @CNN Thank you for showing us the ignorance of America and its lower class citizens.",
            "user id": 285462867,
            "user name": "",
            "stance_label": 0,
            "state": 0,
            "hop": 1
        },
        {
            "comment id": 15,
            "parent": -1,
            "children": [],
            "content": "@CNNKatelyn @CNN http://t.co/iJh4Jrnc3w",
            "user id": 1081566840,
            "user name": "",
            "stance_label": 0,
            "state": 0,
            "hop": 1
        },
        {
            "comment id": 16,
            "parent": -1,
            "children": [],
            "content": "@CNNKatelyn @CNN Innocent until proven guilty.",
            "user id": 90888044,
            "user name": "",
            "stance_label": 0,
            "state": 0,
            "hop": 1
        },
        {
            "comment id": 17,
            "parent": -1,
            "children": [],
            "content": "@CNNKatelyn What a ride! What a ride! your tweets takes a center stage on my honorable platform @CouchSurfingEa http://t.co/to3XEtSzXJ",
            "user id": 28103908,
            "user name": "",
            "stance_label": 0,
            "state": 0,
            "hop": 1
        },
        {
            "comment id": 18,
            "parent": -1,
            "children": [],
            "content": "@CNNKatelyn @CNN The sign should say Nor not or.",
            "user id": 60351264,
            "user name": "",
            "stance_label": 0,
            "state": 0,
            "hop": 1
        },
        {
            "comment id": 19,
            "parent": -1,
            "children": [],
            "content": "@CNNKatelyn how!!! How can we not be looking at realizing that an officer was put into a position that was threatening! When do we stand4him",
            "user id": 2311170019,
            "user name": "",
            "stance_label": 0,
            "state": 0,
            "hop": 1
        },
        {
            "comment id": 20,
            "parent": -1,
            "children": [],
            "content": "“@CNNKatelyn: Ferguson police chief speaks with protesters early Friday am. #ferguson http://t.co/1argph63mC” first time?",
            "user id": 536904720,
            "user name": "",
            "stance_label": 0,
            "state": 0,
            "hop": 1
        },
        {
            "comment id": 21,
            "parent": -1,
            "children": [],
            "content": "@CNNKatelyn @CNN when Police will realise this that is the problem till date ?",
            "user id": 2606073998,
            "user name": "",
            "stance_label": 1,
            "state": 1,
            "hop": 1
        },
        {
            "comment id": 22,
            "parent": -1,
            "children": [],
            "content": "@CNNKatelyn @CNN RIGHT!!!!!!!!!!!",
            "user id": 2736897084,
            "user name": "",
            "stance_label": 0,
            "state": 0,
            "hop": 1
        },
        {
            "comment id": 23,
            "parent": 1,
            "children": [
                24
            ],
            "content": "@craignb @CNNKatelyn by upholding the law, that makes them sense them enforcers of the law which makes them the law....",
            "user id": 262094773,
            "user name": "",
            "stance_label": 1,
            "state": 1,
            "hop": 3
        },
        {
            "comment id": 24,
            "parent": 23,
            "children": [
                25
            ],
            "content": "@data1984 @cnnkatelyn lol ok",
            "user id": 18274760,
            "user name": "",
            "stance_label": 1,
            "state": 0,
            "hop": 4
        },
        {
            "comment id": 25,
            "parent": 24,
            "children": [
                26
            ],
            "content": "@craignb @CNNKatelyn a few grammatical mistakes from me there  but I'm sure you got what I was saying",
            "user id": 262094773,
            "user name": "",
            "stance_label": 0,
            "state": 0,
            "hop": 5
        },
        {
            "comment id": 26,
            "parent": 25,
            "children": [],
            "content": "@data1984 @cnnkatelyn I got you.",
            "user id": 18274760,
            "user name": "",
            "stance_label": 0,
            "state": 0,
            "hop": 6
        }
    ],
    "state": {
        "1-hop": {
            "state_0": 13,
            "state_1": 5
        },
        "2-hop": {
            "state_0": 5,
            "state_1": 0
        },
        "3-hop": {
            "state_0": 0,
            "state_1": 1
        },
        "4-hop": {
            "state_0": 1,
            "state_1": 0
        },
        "5-hop": {
            "state_0": 1,
            "state_1": 0
        },
        "6-hop": {
            "state_0": 1,
            "state_1": 0
        }
    }
}